brnolm/__init__.py
brnolm/analysis.py
brnolm/analyze-ivec-changes.py
brnolm/analyze-ivec-distribution.py
brnolm/files-to-bow.py
brnolm/investigate-ivecs.py
brnolm/kaldi_itf.py
brnolm/lm-info.py
brnolm/multifile-ivec-unigram-ppl.py
brnolm/multifile-ml-unigram-ppl.py
brnolm/multifile-ml-unigram-tranfer-ppl.py
brnolm/plotting.py
brnolm/rmn-activation-plotter.py
brnolm/rmn-grad-plotter.py
brnolm/rmn-plotter.py
brnolm/srilm-debug2.py
brnolm/data_pipeline/__init__.py
brnolm/data_pipeline/aug_paper_pipeline.py
brnolm/data_pipeline/augmentation.py
brnolm/data_pipeline/flexible_pipeline.py
brnolm/data_pipeline/masked.py
brnolm/data_pipeline/multistream.py
brnolm/data_pipeline/pipeline_factories.py
brnolm/data_pipeline/reading.py
brnolm/data_pipeline/split_corpus_dataset.py
brnolm/data_pipeline/temporal_splitting.py
brnolm/data_pipeline/threaded.py
brnolm/language_models/__init__.py
brnolm/language_models/decoders.py
brnolm/language_models/encoders.py
brnolm/language_models/ffnn_models.py
brnolm/language_models/language_model.py
brnolm/language_models/lstm_model.py
brnolm/language_models/transformer.py
brnolm/language_models/vocab.py
brnolm/oov_clustering/__init__.py
brnolm/oov_clustering/det.py
brnolm/oov_clustering/embeddings_computation.py
brnolm/oov_clustering/embeddings_io.py
brnolm/oov_clustering/oov_alignment_lib.py
brnolm/rescoring/segment_scoring.py
brnolm/runtime/__init__.py
brnolm/runtime/evaluation.py
brnolm/runtime/loggers.py
brnolm/runtime/model_statistics.py
brnolm/runtime/reporting.py
brnolm/runtime/runtime_multifile.py
brnolm/runtime/runtime_utils.py
brnolm/runtime/tensor_reorganization.py
brnolm/smm_itf/__init__.py
brnolm/smm_itf/ivec_appenders.py
brnolm/smm_itf/pack-smm.py
brnolm/smm_itf/smm_ivec_extractor.py
brnolm/smm_itf/xtract-ivecs-example.py
brnolm-0.3.0.dist-info/LICENSE
brnolm-0.3.0.dist-info/METADATA
brnolm-0.3.0.dist-info/WHEEL
brnolm-0.3.0.dist-info/top_level.txt
brnolm-0.3.0.dist-info/RECORD
