Metadata-Version: 2.1
Name: brnolm
Version: 0.3.0
Summary: A language modeling toolit
Author-email: Karel Beneš <ibenes@fit.vutbr.cz>
License: MIT License
Project-URL: repository, https://github.com/BUTSpeechFIT/BrnoLM
Keywords: language modeling
Classifier: Programming Language :: Python :: 3
Classifier: License :: OSI Approved :: MIT License
Classifier: Operating System :: POSIX
Requires-Python: >=3.6
License-File: LICENSE
Requires-Dist: numpy
Requires-Dist: torch (>=1.4)
Requires-Dist: scikit-learn
